Metadata-Version: 2.1
Name: perrot
Version: 0.25.0
Summary: Draw simple plots using Pero drawing library
Home-page: https://github.com/xxao/perrot
Author: Martin Strohalm
Author-email: 
License: MIT
Classifier: Development Status :: 3 - Alpha
Classifier: Programming Language :: Python :: 3 :: Only
Classifier: Operating System :: OS Independent
Classifier: Topic :: Multimedia :: Graphics :: Presentation
Classifier: Topic :: Scientific/Engineering
Classifier: Intended Audience :: Developers
Classifier: Intended Audience :: Science/Research
License-File: LICENSE
Requires-Dist: numpy
Requires-Dist: pero
